unigame/__init__.py
unipy/__init__.py
unithon/__init__.py
unigame-0.1.dist-info/METADATA
unigame-0.1.dist-info/WHEEL
unigame-0.1.dist-info/top_level.txt
unigame-0.1.dist-info/RECORD
