Metadata-Version: 2.1
Name: unigame
Version: 0.1
Requires-Dist: pygame >=2.5.2
